convoke/__init__.py
convoke/bases.py
convoke/configs.py
convoke/docs.py
convoke/inspectors.py
convoke/mountpoints.py
convoke/plugins.py
convoke/sentinels.py
convoke/signals.py
convoke-2.2.9.dist-info/LICENSE.md
convoke-2.2.9.dist-info/METADATA
convoke-2.2.9.dist-info/WHEEL
convoke-2.2.9.dist-info/RECORD
