Metadata-Version: 2.1
Name: convoke
Version: 2.2.9
Summary: A Python app configuration toolkit that tries to do things right.
Home-page: https://github.com/eykd/convoke/
License: BSD
Author: David Eyk
Author-email: david@worldsenoughstudios.com
Requires-Python: >=3.11,<4.0
Classifier: Development Status :: 4 - Beta
Classifier: Environment :: Plugins
Classifier: License :: OSI Approved :: BSD License
Classifier: License :: Other/Proprietary License
Classifier: Programming Language :: Python :: 3
Classifier: Programming Language :: Python :: 3.11
Classifier: Programming Language :: Python :: 3.12
Classifier: Topic :: Software Development :: Libraries :: Application Frameworks
Classifier: Topic :: Software Development :: Libraries :: Python Modules
Requires-Dist: funcy (>=2.0,<3.0)
Project-URL: Documentation, https://eykd.github.io/convoke/latest/
Project-URL: Repository, https://github.com/eykd/convoke
